netbox_cluster/__init__.py
netbox_cluster/api/__init__.py
netbox_cluster/api/nested_serializers.py
netbox_cluster/api/serializers.py
netbox_cluster/api/urls.py
netbox_cluster/api/views.py
netbox_cluster/choices.py
netbox_cluster/filtersets.py
netbox_cluster/migrations/0001_initial.py
netbox_cluster/migrations/__init__.py
netbox_cluster/models/__init__.py
netbox_cluster/models/clusters.py
netbox_cluster/tests/__init__.py
netbox_cluster/tests/test_api.py
netbox_cluster/tests/test_filtersets.py
netbox_cluster/tests/test_models.py
netbox_cluster-0.1.2.dist-info/LICENSE
netbox_cluster-0.1.2.dist-info/WHEEL
netbox_cluster-0.1.2.dist-info/METADATA
netbox_cluster-0.1.2.dist-info/RECORD
