Metadata-Version: 2.1
Name: netbox-cluster
Version: 0.1.2
Summary: 
Author: Pat McLean
Author-email: patrick.mclean@sap.com
Requires-Python: >=3.10,<4.0
Classifier: Programming Language :: Python :: 3
Classifier: Programming Language :: Python :: 3.10
Classifier: Programming Language :: Python :: 3.11
Requires-Dist: bleach (==6.0.0)
Requires-Dist: boto3 (==1.28.26)
Requires-Dist: django (==4.2.5)
Requires-Dist: django-cors-headers (==4.2.0)
Requires-Dist: django-debug-toolbar (==4.2.0)
Requires-Dist: django-filter (==23.2)
Requires-Dist: django-graphiql-debug-toolbar (==0.2.0)
Requires-Dist: django-mptt (==0.14)
Requires-Dist: django-pglocks (==1.0.4)
Requires-Dist: django-prometheus (==2.3.1)
Requires-Dist: django-redis (==5.3.0)
Requires-Dist: django-rich (==1.7.0)
Requires-Dist: django-rq (==2.8.1)
Requires-Dist: django-tables2 (==2.6.0)
Requires-Dist: django-taggit (==4.0.0)
Requires-Dist: django-timezone-field (==6.0)
Requires-Dist: djangorestframework (==3.14.0)
Requires-Dist: drf-spectacular (==0.26.4)
Requires-Dist: drf-spectacular-sidecar (==2023.9.1)
Requires-Dist: dulwich (==0.21.5)
Requires-Dist: feedparser (==6.0.10)
Requires-Dist: graphene-django (==3.0.0)
Requires-Dist: gunicorn (==21.2.0)
Requires-Dist: jinja2 (==3.1.2)
Requires-Dist: markdown (==3.3.7)
Requires-Dist: netaddr (==0.8.0)
Requires-Dist: pillow (==10.0.0)
Requires-Dist: psycopg[binary,pool] (==3.1.10)
Requires-Dist: pyyaml (==6.0.1)
Requires-Dist: sentry-sdk (==1.30.0)
Requires-Dist: social-auth-app-django (==5.3.0)
Requires-Dist: social-auth-core[openidconnect] (==4.4.2)
Requires-Dist: svgwrite (==1.4.3)
Requires-Dist: tablib (==3.5.0)
Requires-Dist: tzdata (==2023.3)
